{"nodes": [{"id": "users_mikel_brostrom_boxmot_boxmot_postprocessing_registry_py", "label": "registry.py", "file_type": "code", "source_file": "postprocessing/registry.py", "source_location": "L1"}, {"id": "postprocessing_registry_supported_postprocessors", "label": "supported_postprocessors()", "file_type": "code", "source_file": "postprocessing/registry.py", "source_location": "L10"}, {"id": "postprocessing_registry_create_postprocessor", "label": "create_postprocessor()", "file_type": "code", "source_file": "postprocessing/registry.py", "source_location": "L15"}, {"id": "any", "label": "Any", "file_type": "code", "source_file": "", "source_location": ""}, {"id": "postprocessor", "label": "Postprocessor", "file_type": "code", "source_file": "", "source_location": ""}, {"id": "postprocessing_registry_rationale_11", "label": "Return supported postprocessing step names.", "file_type": "rationale", "source_file": "postprocessing/registry.py", "source_location": "L11"}, {"id": "postprocessing_registry_rationale_16", "label": "Create a postprocessor by name.", "file_type": "rationale", "source_file": "postprocessing/registry.py", "source_location": "L16"}], "edges": [{"source": "users_mikel_brostrom_boxmot_boxmot_postprocessing_registry_py", "target": "typing", "relation": "imports_from", "context": "import", "confidence": "EXTRACTED", "source_file": "postprocessing/registry.py", "source_location": "L3", "weight": 1.0}, {"source": "users_mikel_brostrom_boxmot_boxmot_postprocessing_registry_py", "target": "boxmot_postprocessing_base", "relation": "imports_from", "context": "import", "confidence": "EXTRACTED", "source_file": "postprocessing/registry.py", "source_location": "L5", "weight": 1.0}, {"source": "users_mikel_brostrom_boxmot_boxmot_postprocessing_registry_py", "target": "postprocessing_registry_supported_postprocessors", "relation": "contains", "confidence": "EXTRACTED", "source_file": "postprocessing/registry.py", "source_location": "L10", "weight": 1.0}, {"source": "users_mikel_brostrom_boxmot_boxmot_postprocessing_registry_py", "target": "postprocessing_registry_create_postprocessor", "relation": "contains", "confidence": "EXTRACTED", "source_file": "postprocessing/registry.py", "source_location": "L15", "weight": 1.0}, {"source": "postprocessing_registry_create_postprocessor", "target": "any", "relation": "references", "context": "parameter_type", "confidence": "EXTRACTED", "source_file": "postprocessing/registry.py", "source_location": "L15", "weight": 1.0}, {"source": "postprocessing_registry_create_postprocessor", "target": "postprocessor", "relation": "references", "context": "return_type", "confidence": "EXTRACTED", "source_file": "postprocessing/registry.py", "source_location": "L15", "weight": 1.0}, {"source": "postprocessing_registry_rationale_11", "target": "postprocessing_registry_supported_postprocessors", "relation": "rationale_for", "confidence": "EXTRACTED", "source_file": "postprocessing/registry.py", "source_location": "L11", "weight": 1.0}, {"source": "postprocessing_registry_rationale_16", "target": "postprocessing_registry_create_postprocessor", "relation": "rationale_for", "confidence": "EXTRACTED", "source_file": "postprocessing/registry.py", "source_location": "L16", "weight": 1.0}], "raw_calls": [{"caller_nid": "postprocessing_registry_create_postprocessor", "callee": "lower", "is_member_call": true, "source_file": "/Users/mikel.brostrom/boxmot/boxmot/postprocessing/registry.py", "source_location": "L17", "receiver": null}, {"caller_nid": "postprocessing_registry_create_postprocessor", "callee": "strip", "is_member_call": true, "source_file": "/Users/mikel.brostrom/boxmot/boxmot/postprocessing/registry.py", "source_location": "L17", "receiver": "name"}, {"caller_nid": "postprocessing_registry_create_postprocessor", "callee": "GSIPostprocessor", "is_member_call": false, "source_file": "/Users/mikel.brostrom/boxmot/boxmot/postprocessing/registry.py", "source_location": "L21", "receiver": null}, {"caller_nid": "postprocessing_registry_create_postprocessor", "callee": "GBRCPostprocessor", "is_member_call": false, "source_file": "/Users/mikel.brostrom/boxmot/boxmot/postprocessing/registry.py", "source_location": "L25", "receiver": null}, {"caller_nid": "postprocessing_registry_create_postprocessor", "callee": "GTAPostprocessor", "is_member_call": false, "source_file": "/Users/mikel.brostrom/boxmot/boxmot/postprocessing/registry.py", "source_location": "L29", "receiver": null}, {"caller_nid": "postprocessing_registry_create_postprocessor", "callee": "ValueError", "is_member_call": false, "source_file": "/Users/mikel.brostrom/boxmot/boxmot/postprocessing/registry.py", "source_location": "L30", "receiver": null}]}