{"nodes": [{"id": "users_mikel_brostrom_boxmot_boxmot_reid_backbones_mobilenetv2_py", "label": "mobilenetv2.py", "file_type": "code", "source_file": "reid/backbones/mobilenetv2.py", "source_location": "L1"}, {"id": "backbones_mobilenetv2_convblock", "label": "ConvBlock", "file_type": "code", "source_file": "reid/backbones/mobilenetv2.py", "source_location": "L19"}, {"id": "backbones_mobilenetv2_convblock_init", "label": ".__init__()", "file_type": "code", "source_file": "reid/backbones/mobilenetv2.py", "source_location": "L34"}, {"id": "backbones_mobilenetv2_convblock_forward", "label": ".forward()", "file_type": "code", "source_file": "reid/backbones/mobilenetv2.py", "source_location": "L39"}, {"id": "backbones_mobilenetv2_bottleneck", "label": "Bottleneck", "file_type": "code", "source_file": "reid/backbones/mobilenetv2.py", "source_location": "L43"}, {"id": "backbones_mobilenetv2_bottleneck_init", "label": ".__init__()", "file_type": "code", "source_file": "reid/backbones/mobilenetv2.py", "source_location": "L44"}, {"id": "backbones_mobilenetv2_bottleneck_forward", "label": ".forward()", "file_type": "code", "source_file": "reid/backbones/mobilenetv2.py", "source_location": "L57"}, {"id": "backbones_mobilenetv2_mobilenetv2", "label": "MobileNetV2", "file_type": "code", "source_file": "reid/backbones/mobilenetv2.py", "source_location": "L67"}, {"id": "backbones_mobilenetv2_mobilenetv2_init", "label": ".__init__()", "file_type": "code", "source_file": "reid/backbones/mobilenetv2.py", "source_location": "L79"}, {"id": "backbones_mobilenetv2_mobilenetv2_make_layer", "label": "._make_layer()", "file_type": "code", "source_file": "reid/backbones/mobilenetv2.py", "source_location": "L110"}, {"id": "backbones_mobilenetv2_mobilenetv2_construct_fc_layer", "label": "._construct_fc_layer()", "file_type": "code", "source_file": "reid/backbones/mobilenetv2.py", "source_location": "L122"}, {"id": "backbones_mobilenetv2_mobilenetv2_init_params", "label": "._init_params()", "file_type": "code", "source_file": "reid/backbones/mobilenetv2.py", "source_location": "L151"}, {"id": "backbones_mobilenetv2_mobilenetv2_featuremaps", "label": ".featuremaps()", "file_type": "code", "source_file": "reid/backbones/mobilenetv2.py", "source_location": "L168"}, {"id": "backbones_mobilenetv2_mobilenetv2_forward", "label": ".forward()", "file_type": "code", "source_file": "reid/backbones/mobilenetv2.py", "source_location": "L180"}, {"id": "backbones_mobilenetv2_init_pretrained_weights", "label": "init_pretrained_weights()", "file_type": "code", "source_file": "reid/backbones/mobilenetv2.py", "source_location": "L201"}, {"id": "backbones_mobilenetv2_mobilenetv2_x1_0", "label": "mobilenetv2_x1_0()", "file_type": "code", "source_file": "reid/backbones/mobilenetv2.py", "source_location": "L217"}, {"id": "backbones_mobilenetv2_mobilenetv2_x1_4", "label": "mobilenetv2_x1_4()", "file_type": "code", "source_file": "reid/backbones/mobilenetv2.py", "source_location": "L233"}, {"id": "backbones_mobilenetv2_rationale_20", "label": "Basic convolutional block.      convolution (bias discarded) + batch normalizati", "file_type": "rationale", "source_file": "reid/backbones/mobilenetv2.py", "source_location": "L20"}, {"id": "backbones_mobilenetv2_rationale_68", "label": "MobileNetV2.      Reference:         Sandler et al. MobileNetV2: Inverted Residu", "file_type": "rationale", "source_file": "reid/backbones/mobilenetv2.py", "source_location": "L68"}, {"id": "backbones_mobilenetv2_rationale_123", "label": "Constructs fully connected layer.          Args:             fc_dims (list or tu", "file_type": "rationale", "source_file": "reid/backbones/mobilenetv2.py", "source_location": "L123"}, {"id": "backbones_mobilenetv2_rationale_202", "label": "Initializes model with pretrained weights.      Layers that don't match with pre", "file_type": "rationale", "source_file": "reid/backbones/mobilenetv2.py", "source_location": "L202"}], "edges": [{"source": "users_mikel_brostrom_boxmot_boxmot_reid_backbones_mobilenetv2_py", "target": "torch_utils_model_zoo", "relation": "imports", "context": "import", "confidence": "EXTRACTED", "source_file": "reid/backbones/mobilenetv2.py", "source_location": "L5", "weight": 1.0}, {"source": "users_mikel_brostrom_boxmot_boxmot_reid_backbones_mobilenetv2_py", "target": "torch", "relation": "imports_from", "context": "import", "confidence": "EXTRACTED", "source_file": "reid/backbones/mobilenetv2.py", "source_location": "L6", "weight": 1.0}, {"source": "users_mikel_brostrom_boxmot_boxmot_reid_backbones_mobilenetv2_py", "target": "torch_nn", "relation": "imports_from", "context": "import", "confidence": "EXTRACTED", "source_file": "reid/backbones/mobilenetv2.py", "source_location": "L7", "weight": 1.0}, {"source": "users_mikel_brostrom_boxmot_boxmot_reid_backbones_mobilenetv2_py", "target": "backbones_mobilenetv2_convblock", "relation": "contains", "confidence": "EXTRACTED", "source_file": "reid/backbones/mobilenetv2.py", "source_location": "L19", "weight": 1.0}, {"source": "backbones_mobilenetv2_convblock", "target": "backbones_mobilenetv2_convblock_init", "relation": "method", "confidence": "EXTRACTED", "source_file": "reid/backbones/mobilenetv2.py", "source_location": "L34", "weight": 1.0}, {"source": "backbones_mobilenetv2_convblock", "target": "backbones_mobilenetv2_convblock_forward", "relation": "method", "confidence": "EXTRACTED", "source_file": "reid/backbones/mobilenetv2.py", "source_location": "L39", "weight": 1.0}, {"source": "users_mikel_brostrom_boxmot_boxmot_reid_backbones_mobilenetv2_py", "target": "backbones_mobilenetv2_bottleneck", "relation": "contains", "confidence": "EXTRACTED", "source_file": "reid/backbones/mobilenetv2.py", "source_location": "L43", "weight": 1.0}, {"source": "backbones_mobilenetv2_bottleneck", "target": "backbones_mobilenetv2_bottleneck_init", "relation": "method", "confidence": "EXTRACTED", "source_file": "reid/backbones/mobilenetv2.py", "source_location": "L44", "weight": 1.0}, {"source": "backbones_mobilenetv2_bottleneck", "target": "backbones_mobilenetv2_bottleneck_forward", "relation": "method", "confidence": "EXTRACTED", "source_file": "reid/backbones/mobilenetv2.py", "source_location": "L57", "weight": 1.0}, {"source": "users_mikel_brostrom_boxmot_boxmot_reid_backbones_mobilenetv2_py", "target": "backbones_mobilenetv2_mobilenetv2", "relation": "contains", "confidence": "EXTRACTED", "source_file": "reid/backbones/mobilenetv2.py", "source_location": "L67", "weight": 1.0}, {"source": "backbones_mobilenetv2_mobilenetv2", "target": "backbones_mobilenetv2_mobilenetv2_init", "relation": "method", "confidence": "EXTRACTED", "source_file": "reid/backbones/mobilenetv2.py", "source_location": "L79", "weight": 1.0}, {"source": "backbones_mobilenetv2_mobilenetv2", "target": "backbones_mobilenetv2_mobilenetv2_make_layer", "relation": "method", "confidence": "EXTRACTED", "source_file": "reid/backbones/mobilenetv2.py", "source_location": "L110", "weight": 1.0}, {"source": "backbones_mobilenetv2_mobilenetv2", "target": "backbones_mobilenetv2_mobilenetv2_construct_fc_layer", "relation": "method", "confidence": "EXTRACTED", "source_file": "reid/backbones/mobilenetv2.py", "source_location": "L122", "weight": 1.0}, {"source": "backbones_mobilenetv2_mobilenetv2", "target": "backbones_mobilenetv2_mobilenetv2_init_params", "relation": "method", "confidence": "EXTRACTED", "source_file": "reid/backbones/mobilenetv2.py", "source_location": "L151", "weight": 1.0}, {"source": "backbones_mobilenetv2_mobilenetv2", "target": "backbones_mobilenetv2_mobilenetv2_featuremaps", "relation": "method", "confidence": "EXTRACTED", "source_file": "reid/backbones/mobilenetv2.py", "source_location": "L168", "weight": 1.0}, {"source": "backbones_mobilenetv2_mobilenetv2", "target": "backbones_mobilenetv2_mobilenetv2_forward", "relation": "method", "confidence": "EXTRACTED", "source_file": "reid/backbones/mobilenetv2.py", "source_location": "L180", "weight": 1.0}, {"source": "users_mikel_brostrom_boxmot_boxmot_reid_backbones_mobilenetv2_py", "target": "backbones_mobilenetv2_init_pretrained_weights", "relation": "contains", "confidence": "EXTRACTED", "source_file": "reid/backbones/mobilenetv2.py", "source_location": "L201", "weight": 1.0}, {"source": "users_mikel_brostrom_boxmot_boxmot_reid_backbones_mobilenetv2_py", "target": "backbones_mobilenetv2_mobilenetv2_x1_0", "relation": "contains", "confidence": "EXTRACTED", "source_file": "reid/backbones/mobilenetv2.py", "source_location": "L217", "weight": 1.0}, {"source": "users_mikel_brostrom_boxmot_boxmot_reid_backbones_mobilenetv2_py", "target": "backbones_mobilenetv2_mobilenetv2_x1_4", "relation": "contains", "confidence": "EXTRACTED", "source_file": "reid/backbones/mobilenetv2.py", "source_location": "L233", "weight": 1.0}, {"source": "backbones_mobilenetv2_convblock_init", "target": "backbones_mobilenetv2_mobilenetv2_init", "relation": "calls", "context": "call", "confidence": "EXTRACTED", "source_file": "reid/backbones/mobilenetv2.py", "source_location": "L35", "weight": 1.0}, {"source": "backbones_mobilenetv2_bottleneck_init", "target": "backbones_mobilenetv2_mobilenetv2_init", "relation": "calls", "context": "call", "confidence": "EXTRACTED", "source_file": "reid/backbones/mobilenetv2.py", "source_location": "L45", "weight": 1.0}, {"source": "backbones_mobilenetv2_bottleneck_init", "target": "backbones_mobilenetv2_convblock", "relation": "calls", "context": "call", "confidence": "EXTRACTED", "source_file": "reid/backbones/mobilenetv2.py", "source_location": "L48", "weight": 1.0}, {"source": "backbones_mobilenetv2_mobilenetv2_init", "target": "backbones_mobilenetv2_convblock", "relation": "calls", "context": "call", "confidence": "EXTRACTED", "source_file": "reid/backbones/mobilenetv2.py", "source_location": "L94", "weight": 1.0}, {"source": "backbones_mobilenetv2_mobilenetv2_init", "target": "backbones_mobilenetv2_mobilenetv2_make_layer", "relation": "calls", "context": "call", "confidence": "EXTRACTED", "source_file": "reid/backbones/mobilenetv2.py", "source_location": "L95", "weight": 1.0}, {"source": "backbones_mobilenetv2_mobilenetv2_init", "target": "backbones_mobilenetv2_mobilenetv2_construct_fc_layer", "relation": "calls", "context": "call", "confidence": "EXTRACTED", "source_file": "reid/backbones/mobilenetv2.py", "source_location": "L105", "weight": 1.0}, {"source": "backbones_mobilenetv2_mobilenetv2_init", "target": "backbones_mobilenetv2_mobilenetv2_init_params", "relation": "calls", "context": "call", "confidence": "EXTRACTED", "source_file": "reid/backbones/mobilenetv2.py", "source_location": "L108", "weight": 1.0}, {"source": "backbones_mobilenetv2_mobilenetv2_forward", "target": "backbones_mobilenetv2_mobilenetv2_featuremaps", "relation": "calls", "context": "call", "confidence": "EXTRACTED", "source_file": "reid/backbones/mobilenetv2.py", "source_location": "L181", "weight": 1.0}, {"source": "backbones_mobilenetv2_mobilenetv2_x1_0", "target": "backbones_mobilenetv2_mobilenetv2", "relation": "calls", "context": "call", "confidence": "EXTRACTED", "source_file": "reid/backbones/mobilenetv2.py", "source_location": "L218", "weight": 1.0}, {"source": "backbones_mobilenetv2_mobilenetv2_x1_4", "target": "backbones_mobilenetv2_mobilenetv2", "relation": "calls", "context": "call", "confidence": "EXTRACTED", "source_file": "reid/backbones/mobilenetv2.py", "source_location": "L234", "weight": 1.0}, {"source": "backbones_mobilenetv2_rationale_20", "target": "backbones_mobilenetv2_convblock", "relation": "rationale_for", "confidence": "EXTRACTED", "source_file": "reid/backbones/mobilenetv2.py", "source_location": "L20", "weight": 1.0}, {"source": "backbones_mobilenetv2_rationale_68", "target": "backbones_mobilenetv2_mobilenetv2", "relation": "rationale_for", "confidence": "EXTRACTED", "source_file": "reid/backbones/mobilenetv2.py", "source_location": "L68", "weight": 1.0}, {"source": "backbones_mobilenetv2_rationale_123", "target": "backbones_mobilenetv2_mobilenetv2_construct_fc_layer", "relation": "rationale_for", "confidence": "EXTRACTED", "source_file": "reid/backbones/mobilenetv2.py", "source_location": "L123", "weight": 1.0}, {"source": "backbones_mobilenetv2_rationale_202", "target": "backbones_mobilenetv2_init_pretrained_weights", "relation": "rationale_for", "confidence": "EXTRACTED", "source_file": "reid/backbones/mobilenetv2.py", "source_location": "L202", "weight": 1.0}], "raw_calls": [{"caller_nid": "backbones_mobilenetv2_convblock_init", "callee": "Conv2d", "is_member_call": true, "source_file": "/Users/mikel.brostrom/boxmot/boxmot/reid/backbones/mobilenetv2.py", "source_location": "L36", "receiver": "nn"}, {"caller_nid": "backbones_mobilenetv2_convblock_init", "callee": "BatchNorm2d", "is_member_call": true, "source_file": "/Users/mikel.brostrom/boxmot/boxmot/reid/backbones/mobilenetv2.py", "source_location": "L37", "receiver": "nn"}, {"caller_nid": "backbones_mobilenetv2_convblock_forward", "callee": "relu6", "is_member_call": true, "source_file": "/Users/mikel.brostrom/boxmot/boxmot/reid/backbones/mobilenetv2.py", "source_location": "L40", "receiver": "F"}, {"caller_nid": "backbones_mobilenetv2_convblock_forward", "callee": "bn", "is_member_call": true, "source_file": "/Users/mikel.brostrom/boxmot/boxmot/reid/backbones/mobilenetv2.py", "source_location": "L40", "receiver": "self"}, {"caller_nid": "backbones_mobilenetv2_convblock_forward", "callee": "conv", "is_member_call": true, "source_file": "/Users/mikel.brostrom/boxmot/boxmot/reid/backbones/mobilenetv2.py", "source_location": "L40", "receiver": "self"}, {"caller_nid": "backbones_mobilenetv2_bottleneck_init", "callee": "Sequential", "is_member_call": true, "source_file": "/Users/mikel.brostrom/boxmot/boxmot/reid/backbones/mobilenetv2.py", "source_location": "L52", "receiver": "nn"}, {"caller_nid": "backbones_mobilenetv2_bottleneck_init", "callee": "Conv2d", "is_member_call": true, "source_file": "/Users/mikel.brostrom/boxmot/boxmot/reid/backbones/mobilenetv2.py", "source_location": "L53", "receiver": "nn"}, {"caller_nid": "backbones_mobilenetv2_bottleneck_init", "callee": "BatchNorm2d", "is_member_call": true, "source_file": "/Users/mikel.brostrom/boxmot/boxmot/reid/backbones/mobilenetv2.py", "source_location": "L54", "receiver": "nn"}, {"caller_nid": "backbones_mobilenetv2_bottleneck_forward", "callee": "conv1", "is_member_call": true, "source_file": "/Users/mikel.brostrom/boxmot/boxmot/reid/backbones/mobilenetv2.py", "source_location": "L58", "receiver": "self"}, {"caller_nid": "backbones_mobilenetv2_bottleneck_forward", "callee": "dwconv2", "is_member_call": true, "source_file": "/Users/mikel.brostrom/boxmot/boxmot/reid/backbones/mobilenetv2.py", "source_location": "L59", "receiver": "self"}, {"caller_nid": "backbones_mobilenetv2_bottleneck_forward", "callee": "conv3", "is_member_call": true, "source_file": "/Users/mikel.brostrom/boxmot/boxmot/reid/backbones/mobilenetv2.py", "source_location": "L60", "receiver": "self"}, {"caller_nid": "backbones_mobilenetv2_mobilenetv2_init", "callee": "AdaptiveAvgPool2d", "is_member_call": true, "source_file": "/Users/mikel.brostrom/boxmot/boxmot/reid/backbones/mobilenetv2.py", "source_location": "L104", "receiver": "nn"}, {"caller_nid": "backbones_mobilenetv2_mobilenetv2_init", "callee": "Linear", "is_member_call": true, "source_file": "/Users/mikel.brostrom/boxmot/boxmot/reid/backbones/mobilenetv2.py", "source_location": "L106", "receiver": "nn"}, {"caller_nid": "backbones_mobilenetv2_mobilenetv2_make_layer", "callee": "append", "is_member_call": true, "source_file": "/Users/mikel.brostrom/boxmot/boxmot/reid/backbones/mobilenetv2.py", "source_location": "L116", "receiver": "layers"}, {"caller_nid": "backbones_mobilenetv2_mobilenetv2_make_layer", "callee": "block", "is_member_call": false, "source_file": "/Users/mikel.brostrom/boxmot/boxmot/reid/backbones/mobilenetv2.py", "source_location": "L116", "receiver": null}, {"caller_nid": "backbones_mobilenetv2_mobilenetv2_make_layer", "callee": "append", "is_member_call": true, "source_file": "/Users/mikel.brostrom/boxmot/boxmot/reid/backbones/mobilenetv2.py", "source_location": "L119", "receiver": "layers"}, {"caller_nid": "backbones_mobilenetv2_mobilenetv2_make_layer", "callee": "block", "is_member_call": false, "source_file": "/Users/mikel.brostrom/boxmot/boxmot/reid/backbones/mobilenetv2.py", "source_location": "L119", "receiver": null}, {"caller_nid": "backbones_mobilenetv2_mobilenetv2_make_layer", "callee": "Sequential", "is_member_call": true, "source_file": "/Users/mikel.brostrom/boxmot/boxmot/reid/backbones/mobilenetv2.py", "source_location": "L120", "receiver": "nn"}, {"caller_nid": "backbones_mobilenetv2_mobilenetv2_construct_fc_layer", "callee": "format", "is_member_call": true, "source_file": "/Users/mikel.brostrom/boxmot/boxmot/reid/backbones/mobilenetv2.py", "source_location": "L136", "receiver": null}, {"caller_nid": "backbones_mobilenetv2_mobilenetv2_construct_fc_layer", "callee": "append", "is_member_call": true, "source_file": "/Users/mikel.brostrom/boxmot/boxmot/reid/backbones/mobilenetv2.py", "source_location": "L140", "receiver": "layers"}, {"caller_nid": "backbones_mobilenetv2_mobilenetv2_construct_fc_layer", "callee": "Linear", "is_member_call": true, "source_file": "/Users/mikel.brostrom/boxmot/boxmot/reid/backbones/mobilenetv2.py", "source_location": "L140", "receiver": "nn"}, {"caller_nid": "backbones_mobilenetv2_mobilenetv2_construct_fc_layer", "callee": "append", "is_member_call": true, "source_file": "/Users/mikel.brostrom/boxmot/boxmot/reid/backbones/mobilenetv2.py", "source_location": "L141", "receiver": "layers"}, {"caller_nid": "backbones_mobilenetv2_mobilenetv2_construct_fc_layer", "callee": "BatchNorm1d", "is_member_call": true, "source_file": "/Users/mikel.brostrom/boxmot/boxmot/reid/backbones/mobilenetv2.py", "source_location": "L141", "receiver": "nn"}, {"caller_nid": "backbones_mobilenetv2_mobilenetv2_construct_fc_layer", "callee": "append", "is_member_call": true, "source_file": "/Users/mikel.brostrom/boxmot/boxmot/reid/backbones/mobilenetv2.py", "source_location": "L142", "receiver": "layers"}, {"caller_nid": "backbones_mobilenetv2_mobilenetv2_construct_fc_layer", "callee": "ReLU", "is_member_call": true, "source_file": "/Users/mikel.brostrom/boxmot/boxmot/reid/backbones/mobilenetv2.py", "source_location": "L142", "receiver": "nn"}, {"caller_nid": "backbones_mobilenetv2_mobilenetv2_construct_fc_layer", "callee": "append", "is_member_call": true, "source_file": "/Users/mikel.brostrom/boxmot/boxmot/reid/backbones/mobilenetv2.py", "source_location": "L144", "receiver": "layers"}, {"caller_nid": "backbones_mobilenetv2_mobilenetv2_construct_fc_layer", "callee": "Dropout", "is_member_call": true, "source_file": "/Users/mikel.brostrom/boxmot/boxmot/reid/backbones/mobilenetv2.py", "source_location": "L144", "receiver": "nn"}, {"caller_nid": "backbones_mobilenetv2_mobilenetv2_construct_fc_layer", "callee": "Sequential", "is_member_call": true, "source_file": "/Users/mikel.brostrom/boxmot/boxmot/reid/backbones/mobilenetv2.py", "source_location": "L149", "receiver": "nn"}, {"caller_nid": "backbones_mobilenetv2_mobilenetv2_init_params", "callee": "modules", "is_member_call": true, "source_file": "/Users/mikel.brostrom/boxmot/boxmot/reid/backbones/mobilenetv2.py", "source_location": "L152", "receiver": "self"}, {"caller_nid": "backbones_mobilenetv2_mobilenetv2_init_params", "callee": "kaiming_normal_", "is_member_call": true, "source_file": "/Users/mikel.brostrom/boxmot/boxmot/reid/backbones/mobilenetv2.py", "source_location": "L154", "receiver": null}, {"caller_nid": "backbones_mobilenetv2_mobilenetv2_init_params", "callee": "constant_", "is_member_call": true, "source_file": "/Users/mikel.brostrom/boxmot/boxmot/reid/backbones/mobilenetv2.py", "source_location": "L156", "receiver": null}, {"caller_nid": "backbones_mobilenetv2_mobilenetv2_init_params", "callee": "constant_", "is_member_call": true, "source_file": "/Users/mikel.brostrom/boxmot/boxmot/reid/backbones/mobilenetv2.py", "source_location": "L158", "receiver": null}, {"caller_nid": "backbones_mobilenetv2_mobilenetv2_init_params", "callee": "constant_", "is_member_call": true, "source_file": "/Users/mikel.brostrom/boxmot/boxmot/reid/backbones/mobilenetv2.py", "source_location": "L159", "receiver": null}, {"caller_nid": "backbones_mobilenetv2_mobilenetv2_init_params", "callee": "constant_", "is_member_call": true, "source_file": "/Users/mikel.brostrom/boxmot/boxmot/reid/backbones/mobilenetv2.py", "source_location": "L161", "receiver": null}, {"caller_nid": "backbones_mobilenetv2_mobilenetv2_init_params", "callee": "constant_", "is_member_call": true, "source_file": "/Users/mikel.brostrom/boxmot/boxmot/reid/backbones/mobilenetv2.py", "source_location": "L162", "receiver": null}, {"caller_nid": "backbones_mobilenetv2_mobilenetv2_init_params", "callee": "normal_", "is_member_call": true, "source_file": "/Users/mikel.brostrom/boxmot/boxmot/reid/backbones/mobilenetv2.py", "source_location": "L164", "receiver": null}, {"caller_nid": "backbones_mobilenetv2_mobilenetv2_init_params", "callee": "constant_", "is_member_call": true, "source_file": "/Users/mikel.brostrom/boxmot/boxmot/reid/backbones/mobilenetv2.py", "source_location": "L166", "receiver": null}, {"caller_nid": "backbones_mobilenetv2_mobilenetv2_featuremaps", "callee": "conv1", "is_member_call": true, "source_file": "/Users/mikel.brostrom/boxmot/boxmot/reid/backbones/mobilenetv2.py", "source_location": "L169", "receiver": "self"}, {"caller_nid": "backbones_mobilenetv2_mobilenetv2_featuremaps", "callee": "conv2", "is_member_call": true, "source_file": "/Users/mikel.brostrom/boxmot/boxmot/reid/backbones/mobilenetv2.py", "source_location": "L170", "receiver": "self"}, {"caller_nid": "backbones_mobilenetv2_mobilenetv2_featuremaps", "callee": "conv3", "is_member_call": true, "source_file": "/Users/mikel.brostrom/boxmot/boxmot/reid/backbones/mobilenetv2.py", "source_location": "L171", "receiver": "self"}, {"caller_nid": "backbones_mobilenetv2_mobilenetv2_featuremaps", "callee": "conv4", "is_member_call": true, "source_file": "/Users/mikel.brostrom/boxmot/boxmot/reid/backbones/mobilenetv2.py", "source_location": "L172", "receiver": "self"}, {"caller_nid": "backbones_mobilenetv2_mobilenetv2_featuremaps", "callee": "conv5", "is_member_call": true, "source_file": "/Users/mikel.brostrom/boxmot/boxmot/reid/backbones/mobilenetv2.py", "source_location": "L173", "receiver": "self"}, {"caller_nid": "backbones_mobilenetv2_mobilenetv2_featuremaps", "callee": "conv6", "is_member_call": true, "source_file": "/Users/mikel.brostrom/boxmot/boxmot/reid/backbones/mobilenetv2.py", "source_location": "L174", "receiver": "self"}, {"caller_nid": "backbones_mobilenetv2_mobilenetv2_featuremaps", "callee": "conv7", "is_member_call": true, "source_file": "/Users/mikel.brostrom/boxmot/boxmot/reid/backbones/mobilenetv2.py", "source_location": "L175", "receiver": "self"}, {"caller_nid": "backbones_mobilenetv2_mobilenetv2_featuremaps", "callee": "conv8", "is_member_call": true, "source_file": "/Users/mikel.brostrom/boxmot/boxmot/reid/backbones/mobilenetv2.py", "source_location": "L176", "receiver": "self"}, {"caller_nid": "backbones_mobilenetv2_mobilenetv2_featuremaps", "callee": "conv9", "is_member_call": true, "source_file": "/Users/mikel.brostrom/boxmot/boxmot/reid/backbones/mobilenetv2.py", "source_location": "L177", "receiver": "self"}, {"caller_nid": "backbones_mobilenetv2_mobilenetv2_forward", "callee": "global_avgpool", "is_member_call": true, "source_file": "/Users/mikel.brostrom/boxmot/boxmot/reid/backbones/mobilenetv2.py", "source_location": "L182", "receiver": "self"}, {"caller_nid": "backbones_mobilenetv2_mobilenetv2_forward", "callee": "flatten", "is_member_call": true, "source_file": "/Users/mikel.brostrom/boxmot/boxmot/reid/backbones/mobilenetv2.py", "source_location": "L183", "receiver": "v"}, {"caller_nid": "backbones_mobilenetv2_mobilenetv2_forward", "callee": "fc", "is_member_call": true, "source_file": "/Users/mikel.brostrom/boxmot/boxmot/reid/backbones/mobilenetv2.py", "source_location": "L186", "receiver": "self"}, {"caller_nid": "backbones_mobilenetv2_mobilenetv2_forward", "callee": "classifier", "is_member_call": true, "source_file": "/Users/mikel.brostrom/boxmot/boxmot/reid/backbones/mobilenetv2.py", "source_location": "L191", "receiver": "self"}, {"caller_nid": "backbones_mobilenetv2_mobilenetv2_forward", "callee": "KeyError", "is_member_call": false, "source_file": "/Users/mikel.brostrom/boxmot/boxmot/reid/backbones/mobilenetv2.py", "source_location": "L198", "receiver": null}, {"caller_nid": "backbones_mobilenetv2_mobilenetv2_forward", "callee": "format", "is_member_call": true, "source_file": "/Users/mikel.brostrom/boxmot/boxmot/reid/backbones/mobilenetv2.py", "source_location": "L198", "receiver": null}, {"caller_nid": "backbones_mobilenetv2_init_pretrained_weights", "callee": "load_url", "is_member_call": true, "source_file": "/Users/mikel.brostrom/boxmot/boxmot/reid/backbones/mobilenetv2.py", "source_location": "L206", "receiver": "model_zoo"}, {"caller_nid": "backbones_mobilenetv2_init_pretrained_weights", "callee": "state_dict", "is_member_call": true, "source_file": "/Users/mikel.brostrom/boxmot/boxmot/reid/backbones/mobilenetv2.py", "source_location": "L207", "receiver": "model"}, {"caller_nid": "backbones_mobilenetv2_init_pretrained_weights", "callee": "items", "is_member_call": true, "source_file": "/Users/mikel.brostrom/boxmot/boxmot/reid/backbones/mobilenetv2.py", "source_location": "L210", "receiver": "pretrain_dict"}, {"caller_nid": "backbones_mobilenetv2_init_pretrained_weights", "callee": "size", "is_member_call": true, "source_file": "/Users/mikel.brostrom/boxmot/boxmot/reid/backbones/mobilenetv2.py", "source_location": "L211", "receiver": null}, {"caller_nid": "backbones_mobilenetv2_init_pretrained_weights", "callee": "size", "is_member_call": true, "source_file": "/Users/mikel.brostrom/boxmot/boxmot/reid/backbones/mobilenetv2.py", "source_location": "L211", "receiver": "v"}, {"caller_nid": "backbones_mobilenetv2_init_pretrained_weights", "callee": "update", "is_member_call": true, "source_file": "/Users/mikel.brostrom/boxmot/boxmot/reid/backbones/mobilenetv2.py", "source_location": "L213", "receiver": "model_dict"}, {"caller_nid": "backbones_mobilenetv2_init_pretrained_weights", "callee": "load_state_dict", "is_member_call": true, "source_file": "/Users/mikel.brostrom/boxmot/boxmot/reid/backbones/mobilenetv2.py", "source_location": "L214", "receiver": "model"}, {"caller_nid": "backbones_mobilenetv2_mobilenetv2_x1_0", "callee": "warn", "is_member_call": true, "source_file": "/Users/mikel.brostrom/boxmot/boxmot/reid/backbones/mobilenetv2.py", "source_location": "L225", "receiver": "warnings"}, {"caller_nid": "backbones_mobilenetv2_mobilenetv2_x1_0", "callee": "format", "is_member_call": true, "source_file": "/Users/mikel.brostrom/boxmot/boxmot/reid/backbones/mobilenetv2.py", "source_location": "L226", "receiver": null}, {"caller_nid": "backbones_mobilenetv2_mobilenetv2_x1_4", "callee": "warn", "is_member_call": true, "source_file": "/Users/mikel.brostrom/boxmot/boxmot/reid/backbones/mobilenetv2.py", "source_location": "L241", "receiver": "warnings"}, {"caller_nid": "backbones_mobilenetv2_mobilenetv2_x1_4", "callee": "format", "is_member_call": true, "source_file": "/Users/mikel.brostrom/boxmot/boxmot/reid/backbones/mobilenetv2.py", "source_location": "L242", "receiver": null}]}