{"nodes": [{"id": "users_mikel_brostrom_boxmot_boxmot_engine_eval_init_py", "label": "__init__.py", "file_type": "code", "source_file": "engine/eval/__init__.py", "source_location": "L1"}, {"id": "eval_init_rationale_1", "label": "Evaluation sub-package: cache generation, replay, and MOT evaluation.", "file_type": "rationale", "source_file": "engine/eval/__init__.py", "source_location": "L1"}], "edges": [{"source": "eval_init_rationale_1", "target": "users_mikel_brostrom_boxmot_boxmot_engine_eval_init_py", "relation": "rationale_for", "confidence": "EXTRACTED", "source_file": "engine/eval/__init__.py", "source_location": "L1", "weight": 1.0}], "raw_calls": []}