{"nodes": [{"id": "users_mikel_brostrom_boxmot_boxmot_reid_backbones_lmbn_bnneck_py", "label": "bnneck.py", "file_type": "code", "source_file": "reid/backbones/lmbn/bnneck.py", "source_location": "L1"}, {"id": "lmbn_bnneck_bnneck", "label": "BNNeck", "file_type": "code", "source_file": "reid/backbones/lmbn/bnneck.py", "source_location": "L6"}, {"id": "lmbn_bnneck_bnneck_init", "label": ".__init__()", "file_type": "code", "source_file": "reid/backbones/lmbn/bnneck.py", "source_location": "L7"}, {"id": "lmbn_bnneck_bnneck_forward", "label": ".forward()", "file_type": "code", "source_file": "reid/backbones/lmbn/bnneck.py", "source_location": "L16"}, {"id": "lmbn_bnneck_bnneck_weights_init_kaiming", "label": ".weights_init_kaiming()", "file_type": "code", "source_file": "reid/backbones/lmbn/bnneck.py", "source_location": "L27"}, {"id": "lmbn_bnneck_bnneck_weights_init_classifier", "label": ".weights_init_classifier()", "file_type": "code", "source_file": "reid/backbones/lmbn/bnneck.py", "source_location": "L41"}, {"id": "lmbn_bnneck_bnneck3", "label": "BNNeck3", "file_type": "code", "source_file": "reid/backbones/lmbn/bnneck.py", "source_location": "L49"}, {"id": "lmbn_bnneck_bnneck3_init", "label": ".__init__()", "file_type": "code", "source_file": "reid/backbones/lmbn/bnneck.py", "source_location": "L50"}, {"id": "lmbn_bnneck_bnneck3_forward", "label": ".forward()", "file_type": "code", "source_file": "reid/backbones/lmbn/bnneck.py", "source_location": "L64"}, {"id": "lmbn_bnneck_bnneck3_weights_init_kaiming", "label": ".weights_init_kaiming()", "file_type": "code", "source_file": "reid/backbones/lmbn/bnneck.py", "source_location": "L77"}, {"id": "lmbn_bnneck_bnneck3_weights_init_classifier", "label": ".weights_init_classifier()", "file_type": "code", "source_file": "reid/backbones/lmbn/bnneck.py", "source_location": "L91"}, {"id": "lmbn_bnneck_classblock", "label": "ClassBlock", "file_type": "code", "source_file": "reid/backbones/lmbn/bnneck.py", "source_location": "L103"}, {"id": "lmbn_bnneck_classblock_init", "label": ".__init__()", "file_type": "code", "source_file": "reid/backbones/lmbn/bnneck.py", "source_location": "L104"}, {"id": "lmbn_bnneck_classblock_forward", "label": ".forward()", "file_type": "code", "source_file": "reid/backbones/lmbn/bnneck.py", "source_location": "L139"}, {"id": "lmbn_bnneck_classblock_weights_init_kaiming", "label": ".weights_init_kaiming()", "file_type": "code", "source_file": "reid/backbones/lmbn/bnneck.py", "source_location": "L149"}, {"id": "lmbn_bnneck_classblock_weights_init_classifier", "label": ".weights_init_classifier()", "file_type": "code", "source_file": "reid/backbones/lmbn/bnneck.py", "source_location": "L162"}], "edges": [{"source": "users_mikel_brostrom_boxmot_boxmot_reid_backbones_lmbn_bnneck_py", "target": "torch", "relation": "imports_from", "context": "import", "confidence": "EXTRACTED", "source_file": "reid/backbones/lmbn/bnneck.py", "source_location": "L3", "weight": 1.0}, {"source": "users_mikel_brostrom_boxmot_boxmot_reid_backbones_lmbn_bnneck_py", "target": "lmbn_bnneck_bnneck", "relation": "contains", "confidence": "EXTRACTED", "source_file": "reid/backbones/lmbn/bnneck.py", "source_location": "L6", "weight": 1.0}, {"source": "lmbn_bnneck_bnneck", "target": "lmbn_bnneck_bnneck_init", "relation": "method", "confidence": "EXTRACTED", "source_file": "reid/backbones/lmbn/bnneck.py", "source_location": "L7", "weight": 1.0}, {"source": "lmbn_bnneck_bnneck", "target": "lmbn_bnneck_bnneck_forward", "relation": "method", "confidence": "EXTRACTED", "source_file": "reid/backbones/lmbn/bnneck.py", "source_location": "L16", "weight": 1.0}, {"source": "lmbn_bnneck_bnneck", "target": "lmbn_bnneck_bnneck_weights_init_kaiming", "relation": "method", "confidence": "EXTRACTED", "source_file": "reid/backbones/lmbn/bnneck.py", "source_location": "L27", "weight": 1.0}, {"source": "lmbn_bnneck_bnneck", "target": "lmbn_bnneck_bnneck_weights_init_classifier", "relation": "method", "confidence": "EXTRACTED", "source_file": "reid/backbones/lmbn/bnneck.py", "source_location": "L41", "weight": 1.0}, {"source": "users_mikel_brostrom_boxmot_boxmot_reid_backbones_lmbn_bnneck_py", "target": "lmbn_bnneck_bnneck3", "relation": "contains", "confidence": "EXTRACTED", "source_file": "reid/backbones/lmbn/bnneck.py", "source_location": "L49", "weight": 1.0}, {"source": "lmbn_bnneck_bnneck3", "target": "lmbn_bnneck_bnneck3_init", "relation": "method", "confidence": "EXTRACTED", "source_file": "reid/backbones/lmbn/bnneck.py", "source_location": "L50", "weight": 1.0}, {"source": "lmbn_bnneck_bnneck3", "target": "lmbn_bnneck_bnneck3_forward", "relation": "method", "confidence": "EXTRACTED", "source_file": "reid/backbones/lmbn/bnneck.py", "source_location": "L64", "weight": 1.0}, {"source": "lmbn_bnneck_bnneck3", "target": "lmbn_bnneck_bnneck3_weights_init_kaiming", "relation": "method", "confidence": "EXTRACTED", "source_file": "reid/backbones/lmbn/bnneck.py", "source_location": "L77", "weight": 1.0}, {"source": "lmbn_bnneck_bnneck3", "target": "lmbn_bnneck_bnneck3_weights_init_classifier", "relation": "method", "confidence": "EXTRACTED", "source_file": "reid/backbones/lmbn/bnneck.py", "source_location": "L91", "weight": 1.0}, {"source": "users_mikel_brostrom_boxmot_boxmot_reid_backbones_lmbn_bnneck_py", "target": "lmbn_bnneck_classblock", "relation": "contains", "confidence": "EXTRACTED", "source_file": "reid/backbones/lmbn/bnneck.py", "source_location": "L103", "weight": 1.0}, {"source": "lmbn_bnneck_classblock", "target": "lmbn_bnneck_classblock_init", "relation": "method", "confidence": "EXTRACTED", "source_file": "reid/backbones/lmbn/bnneck.py", "source_location": "L104", "weight": 1.0}, {"source": "lmbn_bnneck_classblock", "target": "lmbn_bnneck_classblock_forward", "relation": "method", "confidence": "EXTRACTED", "source_file": "reid/backbones/lmbn/bnneck.py", "source_location": "L139", "weight": 1.0}, {"source": "lmbn_bnneck_classblock", "target": "lmbn_bnneck_classblock_weights_init_kaiming", "relation": "method", "confidence": "EXTRACTED", "source_file": "reid/backbones/lmbn/bnneck.py", "source_location": "L149", "weight": 1.0}, {"source": "lmbn_bnneck_classblock", "target": "lmbn_bnneck_classblock_weights_init_classifier", "relation": "method", "confidence": "EXTRACTED", "source_file": "reid/backbones/lmbn/bnneck.py", "source_location": "L162", "weight": 1.0}, {"source": "lmbn_bnneck_bnneck_init", "target": "lmbn_bnneck_classblock_init", "relation": "calls", "context": "call", "confidence": "EXTRACTED", "source_file": "reid/backbones/lmbn/bnneck.py", "source_location": "L8", "weight": 1.0}, {"source": "lmbn_bnneck_bnneck3_init", "target": "lmbn_bnneck_classblock_init", "relation": "calls", "context": "call", "confidence": "EXTRACTED", "source_file": "reid/backbones/lmbn/bnneck.py", "source_location": "L51", "weight": 1.0}], "raw_calls": [{"caller_nid": "lmbn_bnneck_bnneck_init", "callee": "BatchNorm1d", "is_member_call": true, "source_file": "/Users/mikel.brostrom/boxmot/boxmot/reid/backbones/lmbn/bnneck.py", "source_location": "L10", "receiver": "nn"}, {"caller_nid": "lmbn_bnneck_bnneck_init", "callee": "requires_grad_", "is_member_call": true, "source_file": "/Users/mikel.brostrom/boxmot/boxmot/reid/backbones/lmbn/bnneck.py", "source_location": "L11", "receiver": null}, {"caller_nid": "lmbn_bnneck_bnneck_init", "callee": "Linear", "is_member_call": true, "source_file": "/Users/mikel.brostrom/boxmot/boxmot/reid/backbones/lmbn/bnneck.py", "source_location": "L12", "receiver": "nn"}, {"caller_nid": "lmbn_bnneck_bnneck_init", "callee": "apply", "is_member_call": true, "source_file": "/Users/mikel.brostrom/boxmot/boxmot/reid/backbones/lmbn/bnneck.py", "source_location": "L13", "receiver": null}, {"caller_nid": "lmbn_bnneck_bnneck_init", "callee": "apply", "is_member_call": true, "source_file": "/Users/mikel.brostrom/boxmot/boxmot/reid/backbones/lmbn/bnneck.py", "source_location": "L14", "receiver": null}, {"caller_nid": "lmbn_bnneck_bnneck_forward", "callee": "view", "is_member_call": true, "source_file": "/Users/mikel.brostrom/boxmot/boxmot/reid/backbones/lmbn/bnneck.py", "source_location": "L17", "receiver": "x"}, {"caller_nid": "lmbn_bnneck_bnneck_forward", "callee": "size", "is_member_call": true, "source_file": "/Users/mikel.brostrom/boxmot/boxmot/reid/backbones/lmbn/bnneck.py", "source_location": "L17", "receiver": "x"}, {"caller_nid": "lmbn_bnneck_bnneck_forward", "callee": "size", "is_member_call": true, "source_file": "/Users/mikel.brostrom/boxmot/boxmot/reid/backbones/lmbn/bnneck.py", "source_location": "L17", "receiver": "x"}, {"caller_nid": "lmbn_bnneck_bnneck_forward", "callee": "bn", "is_member_call": true, "source_file": "/Users/mikel.brostrom/boxmot/boxmot/reid/backbones/lmbn/bnneck.py", "source_location": "L18", "receiver": "self"}, {"caller_nid": "lmbn_bnneck_bnneck_forward", "callee": "classifier", "is_member_call": true, "source_file": "/Users/mikel.brostrom/boxmot/boxmot/reid/backbones/lmbn/bnneck.py", "source_location": "L21", "receiver": "self"}, {"caller_nid": "lmbn_bnneck_bnneck_forward", "callee": "classifier", "is_member_call": true, "source_file": "/Users/mikel.brostrom/boxmot/boxmot/reid/backbones/lmbn/bnneck.py", "source_location": "L24", "receiver": "self"}, {"caller_nid": "lmbn_bnneck_bnneck_weights_init_kaiming", "callee": "find", "is_member_call": true, "source_file": "/Users/mikel.brostrom/boxmot/boxmot/reid/backbones/lmbn/bnneck.py", "source_location": "L29", "receiver": "classname"}, {"caller_nid": "lmbn_bnneck_bnneck_weights_init_kaiming", "callee": "kaiming_normal_", "is_member_call": true, "source_file": "/Users/mikel.brostrom/boxmot/boxmot/reid/backbones/lmbn/bnneck.py", "source_location": "L30", "receiver": null}, {"caller_nid": "lmbn_bnneck_bnneck_weights_init_kaiming", "callee": "constant_", "is_member_call": true, "source_file": "/Users/mikel.brostrom/boxmot/boxmot/reid/backbones/lmbn/bnneck.py", "source_location": "L31", "receiver": null}, {"caller_nid": "lmbn_bnneck_bnneck_weights_init_kaiming", "callee": "find", "is_member_call": true, "source_file": "/Users/mikel.brostrom/boxmot/boxmot/reid/backbones/lmbn/bnneck.py", "source_location": "L32", "receiver": "classname"}, {"caller_nid": "lmbn_bnneck_bnneck_weights_init_kaiming", "callee": "kaiming_normal_", "is_member_call": true, "source_file": "/Users/mikel.brostrom/boxmot/boxmot/reid/backbones/lmbn/bnneck.py", "source_location": "L33", "receiver": null}, {"caller_nid": "lmbn_bnneck_bnneck_weights_init_kaiming", "callee": "constant_", "is_member_call": true, "source_file": "/Users/mikel.brostrom/boxmot/boxmot/reid/backbones/lmbn/bnneck.py", "source_location": "L35", "receiver": null}, {"caller_nid": "lmbn_bnneck_bnneck_weights_init_kaiming", "callee": "find", "is_member_call": true, "source_file": "/Users/mikel.brostrom/boxmot/boxmot/reid/backbones/lmbn/bnneck.py", "source_location": "L36", "receiver": "classname"}, {"caller_nid": "lmbn_bnneck_bnneck_weights_init_kaiming", "callee": "constant_", "is_member_call": true, "source_file": "/Users/mikel.brostrom/boxmot/boxmot/reid/backbones/lmbn/bnneck.py", "source_location": "L38", "receiver": null}, {"caller_nid": "lmbn_bnneck_bnneck_weights_init_kaiming", "callee": "constant_", "is_member_call": true, "source_file": "/Users/mikel.brostrom/boxmot/boxmot/reid/backbones/lmbn/bnneck.py", "source_location": "L39", "receiver": null}, {"caller_nid": "lmbn_bnneck_bnneck_weights_init_classifier", "callee": "find", "is_member_call": true, "source_file": "/Users/mikel.brostrom/boxmot/boxmot/reid/backbones/lmbn/bnneck.py", "source_location": "L43", "receiver": "classname"}, {"caller_nid": "lmbn_bnneck_bnneck_weights_init_classifier", "callee": "normal_", "is_member_call": true, "source_file": "/Users/mikel.brostrom/boxmot/boxmot/reid/backbones/lmbn/bnneck.py", "source_location": "L44", "receiver": null}, {"caller_nid": "lmbn_bnneck_bnneck_weights_init_classifier", "callee": "constant_", "is_member_call": true, "source_file": "/Users/mikel.brostrom/boxmot/boxmot/reid/backbones/lmbn/bnneck.py", "source_location": "L46", "receiver": null}, {"caller_nid": "lmbn_bnneck_bnneck3_init", "callee": "Conv2d", "is_member_call": true, "source_file": "/Users/mikel.brostrom/boxmot/boxmot/reid/backbones/lmbn/bnneck.py", "source_location": "L56", "receiver": "nn"}, {"caller_nid": "lmbn_bnneck_bnneck3_init", "callee": "BatchNorm1d", "is_member_call": true, "source_file": "/Users/mikel.brostrom/boxmot/boxmot/reid/backbones/lmbn/bnneck.py", "source_location": "L57", "receiver": "nn"}, {"caller_nid": "lmbn_bnneck_bnneck3_init", "callee": "requires_grad_", "is_member_call": true, "source_file": "/Users/mikel.brostrom/boxmot/boxmot/reid/backbones/lmbn/bnneck.py", "source_location": "L59", "receiver": null}, {"caller_nid": "lmbn_bnneck_bnneck3_init", "callee": "Linear", "is_member_call": true, "source_file": "/Users/mikel.brostrom/boxmot/boxmot/reid/backbones/lmbn/bnneck.py", "source_location": "L60", "receiver": "nn"}, {"caller_nid": "lmbn_bnneck_bnneck3_init", "callee": "apply", "is_member_call": true, "source_file": "/Users/mikel.brostrom/boxmot/boxmot/reid/backbones/lmbn/bnneck.py", "source_location": "L61", "receiver": null}, {"caller_nid": "lmbn_bnneck_bnneck3_init", "callee": "apply", "is_member_call": true, "source_file": "/Users/mikel.brostrom/boxmot/boxmot/reid/backbones/lmbn/bnneck.py", "source_location": "L62", "receiver": null}, {"caller_nid": "lmbn_bnneck_bnneck3_forward", "callee": "reduction", "is_member_call": true, "source_file": "/Users/mikel.brostrom/boxmot/boxmot/reid/backbones/lmbn/bnneck.py", "source_location": "L65", "receiver": "self"}, {"caller_nid": "lmbn_bnneck_bnneck3_forward", "callee": "view", "is_member_call": true, "source_file": "/Users/mikel.brostrom/boxmot/boxmot/reid/backbones/lmbn/bnneck.py", "source_location": "L68", "receiver": "x"}, {"caller_nid": "lmbn_bnneck_bnneck3_forward", "callee": "size", "is_member_call": true, "source_file": "/Users/mikel.brostrom/boxmot/boxmot/reid/backbones/lmbn/bnneck.py", "source_location": "L68", "receiver": "x"}, {"caller_nid": "lmbn_bnneck_bnneck3_forward", "callee": "size", "is_member_call": true, "source_file": "/Users/mikel.brostrom/boxmot/boxmot/reid/backbones/lmbn/bnneck.py", "source_location": "L68", "receiver": "x"}, {"caller_nid": "lmbn_bnneck_bnneck3_forward", "callee": "bn", "is_member_call": true, "source_file": "/Users/mikel.brostrom/boxmot/boxmot/reid/backbones/lmbn/bnneck.py", "source_location": "L69", "receiver": "self"}, {"caller_nid": "lmbn_bnneck_bnneck3_forward", "callee": "classifier", "is_member_call": true, "source_file": "/Users/mikel.brostrom/boxmot/boxmot/reid/backbones/lmbn/bnneck.py", "source_location": "L71", "receiver": "self"}, {"caller_nid": "lmbn_bnneck_bnneck3_forward", "callee": "classifier", "is_member_call": true, "source_file": "/Users/mikel.brostrom/boxmot/boxmot/reid/backbones/lmbn/bnneck.py", "source_location": "L74", "receiver": "self"}, {"caller_nid": "lmbn_bnneck_bnneck3_weights_init_kaiming", "callee": "find", "is_member_call": true, "source_file": "/Users/mikel.brostrom/boxmot/boxmot/reid/backbones/lmbn/bnneck.py", "source_location": "L79", "receiver": "classname"}, {"caller_nid": "lmbn_bnneck_bnneck3_weights_init_kaiming", "callee": "kaiming_normal_", "is_member_call": true, "source_file": "/Users/mikel.brostrom/boxmot/boxmot/reid/backbones/lmbn/bnneck.py", "source_location": "L80", "receiver": null}, {"caller_nid": "lmbn_bnneck_bnneck3_weights_init_kaiming", "callee": "constant_", "is_member_call": true, "source_file": "/Users/mikel.brostrom/boxmot/boxmot/reid/backbones/lmbn/bnneck.py", "source_location": "L81", "receiver": null}, {"caller_nid": "lmbn_bnneck_bnneck3_weights_init_kaiming", "callee": "find", "is_member_call": true, "source_file": "/Users/mikel.brostrom/boxmot/boxmot/reid/backbones/lmbn/bnneck.py", "source_location": "L82", "receiver": "classname"}, {"caller_nid": "lmbn_bnneck_bnneck3_weights_init_kaiming", "callee": "kaiming_normal_", "is_member_call": true, "source_file": "/Users/mikel.brostrom/boxmot/boxmot/reid/backbones/lmbn/bnneck.py", "source_location": "L83", "receiver": null}, {"caller_nid": "lmbn_bnneck_bnneck3_weights_init_kaiming", "callee": "constant_", "is_member_call": true, "source_file": "/Users/mikel.brostrom/boxmot/boxmot/reid/backbones/lmbn/bnneck.py", "source_location": "L85", "receiver": null}, {"caller_nid": "lmbn_bnneck_bnneck3_weights_init_kaiming", "callee": "find", "is_member_call": true, "source_file": "/Users/mikel.brostrom/boxmot/boxmot/reid/backbones/lmbn/bnneck.py", "source_location": "L86", "receiver": "classname"}, {"caller_nid": "lmbn_bnneck_bnneck3_weights_init_kaiming", "callee": "constant_", "is_member_call": true, "source_file": "/Users/mikel.brostrom/boxmot/boxmot/reid/backbones/lmbn/bnneck.py", "source_location": "L88", "receiver": null}, {"caller_nid": "lmbn_bnneck_bnneck3_weights_init_kaiming", "callee": "constant_", "is_member_call": true, "source_file": "/Users/mikel.brostrom/boxmot/boxmot/reid/backbones/lmbn/bnneck.py", "source_location": "L89", "receiver": null}, {"caller_nid": "lmbn_bnneck_bnneck3_weights_init_classifier", "callee": "find", "is_member_call": true, "source_file": "/Users/mikel.brostrom/boxmot/boxmot/reid/backbones/lmbn/bnneck.py", "source_location": "L93", "receiver": "classname"}, {"caller_nid": "lmbn_bnneck_bnneck3_weights_init_classifier", "callee": "normal_", "is_member_call": true, "source_file": "/Users/mikel.brostrom/boxmot/boxmot/reid/backbones/lmbn/bnneck.py", "source_location": "L94", "receiver": null}, {"caller_nid": "lmbn_bnneck_bnneck3_weights_init_classifier", "callee": "constant_", "is_member_call": true, "source_file": "/Users/mikel.brostrom/boxmot/boxmot/reid/backbones/lmbn/bnneck.py", "source_location": "L96", "receiver": null}, {"caller_nid": "lmbn_bnneck_classblock_init", "callee": "Linear", "is_member_call": true, "source_file": "/Users/mikel.brostrom/boxmot/boxmot/reid/backbones/lmbn/bnneck.py", "source_location": "L119", "receiver": "nn"}, {"caller_nid": "lmbn_bnneck_classblock_init", "callee": "BatchNorm1d", "is_member_call": true, "source_file": "/Users/mikel.brostrom/boxmot/boxmot/reid/backbones/lmbn/bnneck.py", "source_location": "L123", "receiver": "nn"}, {"caller_nid": "lmbn_bnneck_classblock_init", "callee": "LeakyReLU", "is_member_call": true, "source_file": "/Users/mikel.brostrom/boxmot/boxmot/reid/backbones/lmbn/bnneck.py", "source_location": "L125", "receiver": "nn"}, {"caller_nid": "lmbn_bnneck_classblock_init", "callee": "Dropout", "is_member_call": true, "source_file": "/Users/mikel.brostrom/boxmot/boxmot/reid/backbones/lmbn/bnneck.py", "source_location": "L127", "receiver": "nn"}, {"caller_nid": "lmbn_bnneck_classblock_init", "callee": "Sequential", "is_member_call": true, "source_file": "/Users/mikel.brostrom/boxmot/boxmot/reid/backbones/lmbn/bnneck.py", "source_location": "L128", "receiver": "nn"}, {"caller_nid": "lmbn_bnneck_classblock_init", "callee": "apply", "is_member_call": true, "source_file": "/Users/mikel.brostrom/boxmot/boxmot/reid/backbones/lmbn/bnneck.py", "source_location": "L129", "receiver": "add_block"}, {"caller_nid": "lmbn_bnneck_classblock_init", "callee": "Linear", "is_member_call": true, "source_file": "/Users/mikel.brostrom/boxmot/boxmot/reid/backbones/lmbn/bnneck.py", "source_location": "L132", "receiver": "nn"}, {"caller_nid": "lmbn_bnneck_classblock_init", "callee": "Sequential", "is_member_call": true, "source_file": "/Users/mikel.brostrom/boxmot/boxmot/reid/backbones/lmbn/bnneck.py", "source_location": "L133", "receiver": "nn"}, {"caller_nid": "lmbn_bnneck_classblock_init", "callee": "apply", "is_member_call": true, "source_file": "/Users/mikel.brostrom/boxmot/boxmot/reid/backbones/lmbn/bnneck.py", "source_location": "L134", "receiver": "classifier"}, {"caller_nid": "lmbn_bnneck_classblock_forward", "callee": "add_block", "is_member_call": true, "source_file": "/Users/mikel.brostrom/boxmot/boxmot/reid/backbones/lmbn/bnneck.py", "source_location": "L140", "receiver": "self"}, {"caller_nid": "lmbn_bnneck_classblock_forward", "callee": "squeeze", "is_member_call": true, "source_file": "/Users/mikel.brostrom/boxmot/boxmot/reid/backbones/lmbn/bnneck.py", "source_location": "L140", "receiver": null}, {"caller_nid": "lmbn_bnneck_classblock_forward", "callee": "squeeze", "is_member_call": true, "source_file": "/Users/mikel.brostrom/boxmot/boxmot/reid/backbones/lmbn/bnneck.py", "source_location": "L140", "receiver": "x"}, {"caller_nid": "lmbn_bnneck_classblock_forward", "callee": "classifier", "is_member_call": true, "source_file": "/Users/mikel.brostrom/boxmot/boxmot/reid/backbones/lmbn/bnneck.py", "source_location": "L143", "receiver": "self"}, {"caller_nid": "lmbn_bnneck_classblock_forward", "callee": "classifier", "is_member_call": true, "source_file": "/Users/mikel.brostrom/boxmot/boxmot/reid/backbones/lmbn/bnneck.py", "source_location": "L146", "receiver": "self"}, {"caller_nid": "lmbn_bnneck_classblock_weights_init_kaiming", "callee": "find", "is_member_call": true, "source_file": "/Users/mikel.brostrom/boxmot/boxmot/reid/backbones/lmbn/bnneck.py", "source_location": "L152", "receiver": "classname"}, {"caller_nid": "lmbn_bnneck_classblock_weights_init_kaiming", "callee": "kaiming_normal_", "is_member_call": true, "source_file": "/Users/mikel.brostrom/boxmot/boxmot/reid/backbones/lmbn/bnneck.py", "source_location": "L154", "receiver": null}, {"caller_nid": "lmbn_bnneck_classblock_weights_init_kaiming", "callee": "find", "is_member_call": true, "source_file": "/Users/mikel.brostrom/boxmot/boxmot/reid/backbones/lmbn/bnneck.py", "source_location": "L155", "receiver": "classname"}, {"caller_nid": "lmbn_bnneck_classblock_weights_init_kaiming", "callee": "kaiming_normal_", "is_member_call": true, "source_file": "/Users/mikel.brostrom/boxmot/boxmot/reid/backbones/lmbn/bnneck.py", "source_location": "L156", "receiver": null}, {"caller_nid": "lmbn_bnneck_classblock_weights_init_kaiming", "callee": "constant_", "is_member_call": true, "source_file": "/Users/mikel.brostrom/boxmot/boxmot/reid/backbones/lmbn/bnneck.py", "source_location": "L157", "receiver": null}, {"caller_nid": "lmbn_bnneck_classblock_weights_init_kaiming", "callee": "find", "is_member_call": true, "source_file": "/Users/mikel.brostrom/boxmot/boxmot/reid/backbones/lmbn/bnneck.py", "source_location": "L158", "receiver": "classname"}, {"caller_nid": "lmbn_bnneck_classblock_weights_init_kaiming", "callee": "normal_", "is_member_call": true, "source_file": "/Users/mikel.brostrom/boxmot/boxmot/reid/backbones/lmbn/bnneck.py", "source_location": "L159", "receiver": null}, {"caller_nid": "lmbn_bnneck_classblock_weights_init_kaiming", "callee": "constant_", "is_member_call": true, "source_file": "/Users/mikel.brostrom/boxmot/boxmot/reid/backbones/lmbn/bnneck.py", "source_location": "L160", "receiver": null}, {"caller_nid": "lmbn_bnneck_classblock_weights_init_classifier", "callee": "find", "is_member_call": true, "source_file": "/Users/mikel.brostrom/boxmot/boxmot/reid/backbones/lmbn/bnneck.py", "source_location": "L164", "receiver": "classname"}, {"caller_nid": "lmbn_bnneck_classblock_weights_init_classifier", "callee": "normal_", "is_member_call": true, "source_file": "/Users/mikel.brostrom/boxmot/boxmot/reid/backbones/lmbn/bnneck.py", "source_location": "L165", "receiver": null}, {"caller_nid": "lmbn_bnneck_classblock_weights_init_classifier", "callee": "constant_", "is_member_call": true, "source_file": "/Users/mikel.brostrom/boxmot/boxmot/reid/backbones/lmbn/bnneck.py", "source_location": "L166", "receiver": null}]}